rects/__init__.py
rects/region.py
rects-0.2.0.dist-info/LICENSE
rects-0.2.0.dist-info/METADATA
rects-0.2.0.dist-info/WHEEL
rects-0.2.0.dist-info/top_level.txt
rects-0.2.0.dist-info/RECORD
