Metadata-Version: 2.1
Name: rects
Version: 0.2.0
Summary: A library for unions, intersections, subtractions, and xors of rectangles.
Author-email: salt-die <salt-die@protonmail.com>
License: MIT
Project-URL: repository, https://github.com/salt-die/rects
Classifier: Programming Language :: Python :: 3
Classifier: License :: OSI Approved :: MIT License
Classifier: Operating System :: OS Independent
Requires-Python: >=3.12
License-File: LICENSE
